README.txt
setup.py
autologger/__init__.py
autologger.egg-info/PKG-INFO
autologger.egg-info/SOURCES.txt
autologger.egg-info/dependency_links.txt
autologger.egg-info/requires.txt
autologger.egg-info/top_level.txt