Metadata-Version: 1.2
Name: autologger
Version: 0.1.0
Summary: Automatically configure logging
Home-page: https://github.com/matthewh/autologger
Maintainer: Matthew Hershberger
Maintainer-email: matthewh@multipart.net
License: COMPANY-PROPRIETARY
Platform: UNKNOWN
